plm_entropy/__init__.py
plm_entropy/functions.py
plm_entropy-0.2.dist-info/licenses/LICENSE
plm_entropy-0.2.dist-info/METADATA
plm_entropy-0.2.dist-info/WHEEL
plm_entropy-0.2.dist-info/top_level.txt
plm_entropy-0.2.dist-info/RECORD
