Metadata-Version: 2.4
Name: plm_entropy
Version: 0.2
Summary: The pLM entropy Python package
Home-page: https://github.com/spyros-lytras/plm_entropy
Download-URL: https://github.com/spyros-lytras/plm_entropy/dist/plm_entropy-0.1.tar.gz
Author: Spyros Lytras
Author-email: spyros@ims.u-tokyo.ac.jp
License: MIT
Project-URL: Documentation, https://github.com/spyros-lytras/plm_entropy
Keywords: pLM LLM viruses conservation protein
Classifier: Intended Audience :: Science/Research
Classifier: Topic :: Scientific/Engineering :: Bio-Informatics
Classifier: Programming Language :: Python
Requires-Python: ~=3.12
License-File: LICENSE
Requires-Dist: biopython==1.83
Requires-Dist: pandas==2.2.2
Requires-Dist: numpy==1.26.4
Requires-Dist: fair-esm==2.0.0
Requires-Dist: transformers==4.41.2
Requires-Dist: scipy==1.13.1
Requires-Dist: torch==2.3.1
Requires-Dist: typing-extensions==4.12.2
Requires-Dist: sentencepiece==0.2.0
Dynamic: author
Dynamic: author-email
Dynamic: classifier
Dynamic: description
Dynamic: description-content-type
Dynamic: download-url
Dynamic: home-page
Dynamic: keywords
Dynamic: license
Dynamic: license-file
Dynamic: project-url
Dynamic: requires-dist
Dynamic: requires-python
Dynamic: summary
